{
  "id": "ai-hanmi",
  "slug": "ai-hanmi",
  "romaji": "Ai-hanmi",
  "jp": "相半身",
  "category": "stance",
  "def": {
    "en": "Same-lead facing: both partners share the same front foot.",
    "de": "Gleichführige Stellung: beide Partner mit demselben Bein vorn."
  },
  "literal": {
    "en": "mutual/same + half-body",
    "de": "gemeinsam/gleich + Halbkörper"
  },
  "notes": {
    "en": "Parallel lines and mirrored guards. Outside entries (soto irimi/tenkan) are naturally available; inside entries are tighter and often supported by atemi. Maintain center-to-center alignment and avoid crossing your own line when changing leads.",
    "de": "Parallele Linien und gespiegelte Guard. Außen-Einstiege (soto irimi/tenkan) bieten sich an; Innen-Einstiege sind enger und oft durch Atemi unterstützt. Zentrum-zu-Zentrum halten und beim Führungswechsel die eigene Linie nicht kreuzen."
  }
}
