{
  "id": "ai-hanmi-katate-tori",
  "slug": "ai-hanmi-katate-tori",
  "romaji": "Ai-hanmi Katate-tori",
  "jp": "相半身片手取り",
  "category": "attack",
  "def": {
    "en": "Same-lead one-hand wrist grab (R-R/L-L).",
    "de": "Gleichständiger Einhand-Handgelenkgriff (R-R/L-L)."
  },
  "literal": {
    "en": "mutual/same + half-body (stance) + one hand + seize",
    "de": "gemeinsam/gleich + Halbkörper (Stellung) + eine Hand + greifen"
  },
  "notes": {
    "en": "Lines are parallel; outside path is open for irimi or tenkan. Connect through the forearm to your center—no arm-only tugging; keep elbows heavy. Typical follow-ups: ikkyo/nikyo/yonkyo, shiho-nage, kaiten-nage, irimi-nage. Contrast with gyaku-hanmi katate-tori (opposite lead), which flips the entering angles and inside/outside options.",
    "de": "Parallele Linien; Außenbahn ist offen für irimi oder tenkan. Verbindung über den Unterarm bis ins Zentrum – kein reines Ziehen; Ellbogen „schwer“. Typische Weiterführungen: ikkyo/nikyo/yonkyo, shiho-nage, kaiten-nage, irimi-nage. Abgrenzung zu gyaku-hanmi katate-tori (gegenläufige Führung), das Eintrittswinkel und Innen/Außen-Optionen verändert."
  }
}
