{
  "id": "sankyo",
  "slug": "sankyo",
  "romaji": "Sankyō",
  "jp": "三教",
  "category": "other",
  "def": {
    "en": "Third control: spiral up the arm to the shoulder, leading posture.",
    "de": "Dritte Kontrolle: Spiralhebel über den Arm bis zur Schulter, führt die Haltung."
  },
  "literal": { "en": "third + teaching", "de": "drittes + Lehren" },
  "notes": {
    "en": "Also known as kote-hineri in some lines. The spiral winds the forearm and orients the elbow down to steer the shoulder and spine. Study continuous, small-circle rotation from the hips/center with stable posture and clear tap safety—structure over pain. Transfers cleanly to tanto defenses and weapon disarms because the spiral keeps the ‘edge’ off your body. Frequent errors: breaking the spiral into stops, over-gripping the hand, or lifting the elbow away from your body.",
    "de": "In manchen Linien auch kote-hineri genannt. Die Spirale „wickelt“ den Unterarm, richtet den Ellbogen nach unten und steuert Schulter und Wirbelsäule. Übe kontinuierliche Kleinkreisdrehung aus Hüfte/Zentrum, stabile Haltung und klare Abklopf-Sicherheit – Struktur statt Schmerz. Überträgt sich gut auf Tantō-Abwehr und Entwaffnungen, da die Spirale die „Schneide“ vom Körper fernhält. Häufige Fehler: die Spirale in Stopps zerlegen, die Hand „zuklammern“ oder den Ellbogen vom Körper abheben."
  }
}
